bennycloth/AISCutility.py
bennycloth/ASCEutility.py
bennycloth/CanvasUtility.py
bennycloth/Confined.py
bennycloth/NDSutility.py
bennycloth/RCutility.py
bennycloth/TDConcrete.py
bennycloth/__init__.py
bennycloth/beaverframe/__init__.py
bennycloth/beaverframe/convertToOpenSees.py
bennycloth/concrete/Confined.py
bennycloth/concrete/__init__.py
bennycloth/images/__init__.py
bennycloth/images/pixelate.py
bennycloth/matrix/__init__.py
bennycloth/matrix/spy.py
bennycloth/timeseries/__init__.py
bennycloth/timeseries/generatepeaks.py
bennycloth/timeseries/whitenoise.py
bennycloth-0.0.20.dist-info/licenses/LICENSE
src/ASCEutility.py
src/CanvasUtility.py
src/RCutility.py
src/TDConcrete.py
src/__init__.py
src/concrete/Confined.py
src/concrete/RCutility.py
src/concrete/TDConcrete.py
src/concrete/__init__.py
bennycloth-0.0.20.dist-info/METADATA
bennycloth-0.0.20.dist-info/WHEEL
bennycloth-0.0.20.dist-info/top_level.txt
bennycloth-0.0.20.dist-info/RECORD
