Metadata-Version: 2.4
Name: bennycloth
Version: 0.0.20
Summary: A collection of Python functions for structural engineering
Author: Michael H. Scott
Author-email: mhscott@oregonstate.edu
Keywords: python,opensees
Classifier: Programming Language :: Python :: 3
Classifier: Operating System :: OS Independent
Requires-Python: >=3.6
License-File: LICENSE
Requires-Dist: requests
Dynamic: author
Dynamic: author-email
Dynamic: classifier
Dynamic: description
Dynamic: keywords
Dynamic: license-file
Dynamic: requires-dist
Dynamic: requires-python
Dynamic: summary
